pi_mqtt_gpio/__init__.py
pi_mqtt_gpio/scheduler.py
pi_mqtt_gpio/server.py
pi_mqtt_gpio/modules/__init__.py
pi_mqtt_gpio/modules/aht20.py
pi_mqtt_gpio/modules/beaglebone.py
pi_mqtt_gpio/modules/bh1750.py
pi_mqtt_gpio/modules/bme280.py
pi_mqtt_gpio/modules/dht22.py
pi_mqtt_gpio/modules/ds18b.py
pi_mqtt_gpio/modules/gpiod.py
pi_mqtt_gpio/modules/hcsr04.py
pi_mqtt_gpio/modules/lm75.py
pi_mqtt_gpio/modules/mcp3008.py
pi_mqtt_gpio/modules/orangepi.py
pi_mqtt_gpio/modules/pcf8574.py
pi_mqtt_gpio/modules/pcf8575.py
pi_mqtt_gpio/modules/piface2.py
pi_mqtt_gpio/modules/raspberrypi.py
pi_mqtt_gpio/modules/stdio.py
pi_mqtt_gpio/modules/streamserial.py
pi_mqtt_gpio-0.5.6.dist-info/LICENSE
pi_mqtt_gpio-0.5.6.dist-info/METADATA
pi_mqtt_gpio-0.5.6.dist-info/WHEEL
pi_mqtt_gpio-0.5.6.dist-info/entry_points.txt
pi_mqtt_gpio-0.5.6.dist-info/top_level.txt
pi_mqtt_gpio-0.5.6.dist-info/RECORD
